RnaBench/__init__.py
RnaBench/benchmarks.py
RnaBench/benchmarks_test.py
RnaBench/download.py
RnaBench/lib/__init__.py
RnaBench/lib/aggregators.py
RnaBench/lib/alphabets.py
RnaBench/lib/datasets.py
RnaBench/lib/execution.py
RnaBench/lib/feature_extractors.py
RnaBench/lib/metrics.py
RnaBench/lib/metrics_test.py
RnaBench/lib/structural_motifs.py
RnaBench/lib/tasks.py
RnaBench/lib/utils.py
RnaBench/lib/utils_test.py
RnaBench/lib/visualization.py
RnaBench/lib/data/__init__.py
RnaBench/lib/data/build_cm.py
RnaBench/lib/data/build_dataset.py
RnaBench/lib/data/pre_processing.py
RnaBench/lib/data/similarity.py
RnaBench/lib/data/structure_annotation.py
RnaBench/lib/data/parser/__init__.py
RnaBench/lib/data/parser/base_parser.py
RnaBench/lib/data/parser/blast_tab_parser.py
RnaBench/lib/data/parser/cd_hit_clstr_parser.py
RnaBench/lib/data/parser/infernal_tblout_parser.py
RnaBench/lib/data/parser/pdb_parser.py
RnaBench/lib/data/threedee/__init__.py
RnaBench/lib/data/threedee/data.py
RnaBench/lib/rna_design_algorithms/__init__.py
RnaBench/lib/rna_design_algorithms/antarna.py
RnaBench/lib/rna_design_algorithms/eternabrain.py
RnaBench/lib/rna_design_algorithms/gca.py
RnaBench/lib/rna_design_algorithms/mctsrna.py
RnaBench/lib/rna_design_algorithms/riboswitch_design.py
RnaBench/lib/rna_design_algorithms/rnainverse.py
RnaBench/lib/rna_design_algorithms/sentrna.py
RnaBench/lib/rna_folding_algorithms/__init__.py
RnaBench/lib/rna_folding_algorithms/centroidalifold.py
RnaBench/lib/rna_folding_algorithms/centroidfold.py
RnaBench/lib/rna_folding_algorithms/contrafold.py
RnaBench/lib/rna_folding_algorithms/ipknot.py
RnaBench/lib/rna_folding_algorithms/linearfold.py
RnaBench/lib/rna_folding_algorithms/pkiss.py
RnaBench/lib/rna_folding_algorithms/rnaalifold.py
RnaBench/lib/rna_folding_algorithms/rnafold.py
RnaBench/lib/rna_folding_algorithms/rnastructure.py
examples/__init__.py
examples/evaluate_all_folding_baselines_example.py
examples/evaluate_all_folding_baselines_example_minimal.py
RnaBench-0.1.2.dist-info/LICENSE
RnaBench-0.1.2.dist-info/METADATA
RnaBench-0.1.2.dist-info/WHEEL
RnaBench-0.1.2.dist-info/top_level.txt
RnaBench-0.1.2.dist-info/RECORD
