Metadata-Version: 2.1
Name: RnaBench
Version: 0.1.2
Summary: RNA benchmarking tools and utilities.
Home-page: https://github.com/Rungetf/RnaBench.git
Author: Karim Farid
Author-email: faridk@informatik.uni-freiburg.de
License: MIT
Keywords: RNA benchmarking
Classifier: Programming Language :: Python :: 3.9
License-File: LICENSE
Requires-Dist: forgi ==2.0.2
Requires-Dist: ViennaRNA
Requires-Dist: biopython
Requires-Dist: dask
Requires-Dist: nltk ==3.8.1
Requires-Dist: regex ==2022.10.31
Requires-Dist: Distance ==0.1.3
Requires-Dist: distlib ==0.3.6
Requires-Dist: gdown ==4.6.4
Requires-Dist: google-auth ==2.19.1
Requires-Dist: google-auth-oauthlib ==1.0.0
Requires-Dist: google-pasta ==0.2.0
Requires-Dist: GraKeL ==0.1.9
Requires-Dist: numpy ==1.23.5
Requires-Dist: pandas ==1.5.3
Requires-Dist: pyaml ==21.10.1
Requires-Dist: pynisher ==1.0.2
Requires-Dist: pytest
Requires-Dist: PyYAML
Requires-Dist: torch ==1.13.1
Requires-Dist: torchvision ==0.14.1
